aios/__init__.py
aios/utils.py
aios_lib-0.0.6.dist-info/LICENSE
aios_lib-0.0.6.dist-info/METADATA
aios_lib-0.0.6.dist-info/WHEEL
aios_lib-0.0.6.dist-info/top_level.txt
aios_lib-0.0.6.dist-info/RECORD
