Metadata-Version: 2.1
Name: aios-lib
Version: 0.0.6
Summary: aios lib package
Home-page: https://www.clustarai.com
Author: Zhang Manni
Author-email: mandy.zhang@clustar.ai
License: UNKNOWN
Platform: UNKNOWN
Classifier: Programming Language :: Python 
Classifier: License :: OSI Approved :: MIT License
Classifier: Operating System :: OS Independent
